moody/__init__.py
moody/cli.py
moody/core.py
moodylang-0.1.0.dist-info/METADATA
moodylang-0.1.0.dist-info/WHEEL
moodylang-0.1.0.dist-info/entry_points.txt
moodylang-0.1.0.dist-info/top_level.txt
moodylang-0.1.0.dist-info/RECORD
