Metadata-Version: 2.1
Name: moodylang
Version: 0.1.0
Summary: A polite emotional programming language interpreter
Author: Your Name
Classifier: Programming Language :: Python :: 3
Classifier: Operating System :: OS Independent
Requires-Python: >=3.7
